sbcloud/__init__.py
sbcloud/util.py
sbcloud/cli/__init__.py
sbcloud/cli/cookiecutter/cookiecutter.json
sbcloud/cli/cookiecutter/{{ cookiecutter.project_slug }}/README.md
sbcloud/cli/cookiecutter/{{ cookiecutter.project_slug }}/dist_requirements.txt
sbcloud/cli/cookiecutter/{{ cookiecutter.project_slug }}/package.json
sbcloud/cli/cookiecutter/{{ cookiecutter.project_slug }}/setup.py
sbcloud/cli/cookiecutter/{{ cookiecutter.project_slug }}/imports/REMOVE_ME.json
sbcloud/cli/cookiecutter/{{ cookiecutter.project_slug }}/imports/asset.json
sbcloud/cli/cookiecutter/{{ cookiecutter.project_slug }}/imports/sbc_{{ cookiecutter.provider.lower() }}_list_instances.json
sbcloud/cli/cookiecutter/{{ cookiecutter.project_slug }}/imports/sbc_{{ cookiecutter.provider.lower() }}_list_instances.py
sbcloud/cli/cookiecutter/{{ cookiecutter.project_slug }}/imports/sbc_{{ cookiecutter.provider.lower() }}_start_instance.json
sbcloud/cli/cookiecutter/{{ cookiecutter.project_slug }}/imports/sbc_{{ cookiecutter.provider.lower() }}_start_instance.py
sbcloud/cli/cookiecutter/{{ cookiecutter.project_slug }}/imports/sbc_{{ cookiecutter.provider.lower() }}_stop_instance.json
sbcloud/cli/cookiecutter/{{ cookiecutter.project_slug }}/imports/sbc_{{ cookiecutter.provider.lower() }}_stop_instance.py
sbcloud/cli/cookiecutter/{{ cookiecutter.project_slug }}/imports/test_connection.py
sbcloud/cli/cookiecutter/{{ cookiecutter.project_slug }}/sw_{{ cookiecutter.project_slug }}/__init__.py
sbcloud/integrations/__init__.py
sbcloud/integrations/compute.py
sbcloud-0.4.6.dist-info/DESCRIPTION.rst
sbcloud-0.4.6.dist-info/METADATA
sbcloud-0.4.6.dist-info/RECORD
sbcloud-0.4.6.dist-info/WHEEL
sbcloud-0.4.6.dist-info/entry_points.txt
sbcloud-0.4.6.dist-info/metadata.json
sbcloud-0.4.6.dist-info/top_level.txt
