Metadata-Version: 2.0
Name: sbcloud
Version: 0.4.6
Summary: SBCloud
Home-page: UNKNOWN
Author: Swimlane LLC
Author-email: info@swimlane.com
License: UNLICENSED
Platform: UNKNOWN
Classifier: Programming Language :: Python
Classifier: Programming Language :: Python :: 2.7
Requires-Dist: apache-libcloud (==2.2.1)
Requires-Dist: click (<7.0,>=6.0)
Requires-Dist: cookiecutter (<1.7,>=1.6)
